strawberry_sqlalchemy_mapper/__init__.py
strawberry_sqlalchemy_mapper/exc.py
strawberry_sqlalchemy_mapper/field.py
strawberry_sqlalchemy_mapper/loader.py
strawberry_sqlalchemy_mapper/mapper.py
strawberry_sqlalchemy_mapper/ordering.py
strawberry_sqlalchemy_mapper/py.typed
strawberry_sqlalchemy_mapper/relay.py
strawberry_sqlalchemy_mapper/scalars.py
strawberry_sqlalchemy_mapper/utils.py
strawberry_sqlalchemy_mapper-0.6.4.dist-info/AUTHORS.rst
strawberry_sqlalchemy_mapper-0.6.4.dist-info/LICENSE.txt
strawberry_sqlalchemy_mapper-0.6.4.dist-info/METADATA
strawberry_sqlalchemy_mapper-0.6.4.dist-info/WHEEL
strawberry_sqlalchemy_mapper-0.6.4.dist-info/RECORD
