Metadata-Version: 2.3
Name: strawberry-sqlalchemy-mapper
Version: 0.6.4
Summary: A library for autogenerating Strawberry GraphQL types from SQLAlchemy models.
License: MIT
Keywords: graphql,sqlalchemy,strawberry
Author: Tim Dumol
Author-email: tim@timdumol.com
Requires-Python: >=3.8,<4.0
Classifier: Development Status :: 5 - Production/Stable
Classifier: Intended Audience :: Developers
Classifier: License :: OSI Approved :: MIT License
Classifier: Programming Language :: Python :: 3
Classifier: Programming Language :: Python :: 3.8
Classifier: Programming Language :: Python :: 3.9
Classifier: Programming Language :: Python :: 3.10
Classifier: Programming Language :: Python :: 3.11
Classifier: Programming Language :: Python :: 3.12
Classifier: Programming Language :: Python :: 3.13
Classifier: Topic :: Software Development :: Libraries
Classifier: Topic :: Software Development :: Libraries :: Python Modules
Requires-Dist: greenlet (>=3.0.0rc1) ; python_version >= "3.12"
Requires-Dist: sentinel (>=0.3,<1.1)
Requires-Dist: sqlakeyset (>=2.0.1695177552,<3.0.0)
Requires-Dist: sqlalchemy[asyncio] (>=1.4)
Requires-Dist: strawberry-graphql (>=0.236.0)
Project-URL: Changelog, https://strawberry.rocks/changelog
Project-URL: Documentation, https://strawberry.rocks/
Project-URL: Discord, https://discord.com/invite/3uQ2PaY
Project-URL: Homepage, https://strawberry.rocks/
Project-URL: Mastodon, https://farbun.social/@strawberry
Project-URL: Repository, https://github.com/strawberry-graphql/strawberry-sqlalchemy
Project-URL: Sponsor on GitHub, https://github.com/sponsors/strawberry-graphql
Project-URL: Sponsor on Open Collective, https://opencollective.com/strawberry-graphql
Project-URL: Twitter, https://twitter.com/strawberry_gql
